contributors/__init__.py
contributors/cli.py
contributors/contributors.py
contributors-0.3.0.dist-info/DESCRIPTION.rst
contributors-0.3.0.dist-info/METADATA
contributors-0.3.0.dist-info/RECORD
contributors-0.3.0.dist-info/WHEEL
contributors-0.3.0.dist-info/entry_points.txt
contributors-0.3.0.dist-info/metadata.json
contributors-0.3.0.dist-info/top_level.txt
