Metadata-Version: 2.0
Name: contributors
Version: 0.3.0
Summary: A command-line script to get all the contributors for one or more GitHub projects.
Home-page: https://github.com/pydanny/contributors
Author: Daniel Roy Greenfeld
Author-email: pydanny@gmail.com
License: Apache Software License 2.0
Keywords: contributors
Platform: UNKNOWN
Classifier: Development Status :: 2 - Pre-Alpha
Classifier: Intended Audience :: Developers
Classifier: License :: OSI Approved :: Apache Software License
Classifier: Natural Language :: English
Classifier: Programming Language :: Python :: 2
Classifier: Programming Language :: Python :: 2.7
Classifier: Programming Language :: Python :: 3
Classifier: Programming Language :: Python :: 3.3
Classifier: Programming Language :: Python :: 3.4
Classifier: Programming Language :: Python :: 3.5
Requires-Dist: Click (>=6.0)
Requires-Dist: github3.py (==1.0.0a4)
